<?xml version="1.0" encoding="UTF-8"?>
<!DOCTYPE configuration
PUBLIC "-//mybatis.org//DTD Config 3.0//EN"
"http://mybatis.org/dtd/mybatis-3-config.dtd">
<configuration>
	<typeAliases>
		<typeAlias alias="tag" type="com.mtcm.sample.service.vo.Tag" />
		<typeAlias alias="tagcontainer" type="com.mtcm.sample.service.vo.TagContainer" />
		<typeAlias alias="tagmap" type="com.mtcm.sample.service.vo.TagMap" />
		<typeAlias alias="workreport" type="com.mtcm.sample.service.vo.WorkReport" />
		<typeAlias alias="workreportdetail" type="com.mtcm.sample.service.vo.WorkReportDetail" />
	</typeAliases>
	<mappers>
		<mapper resource="tag.xml" />
		<mapper resource="tagcontainer.xml" />
		<mapper resource="tagmap.xml" />
		<mapper resource="workreport.xml" />
		<mapper resource="workreportdetail.xml" />
	</mappers>
</configuration>